google_weather_api/__init__.py
google_weather_api/api.py
google_weather_api/exceptions.py
google_weather_api/model.py
google_weather_api/py.typed
python_google_weather_api-0.0.4.dist-info/licenses/LICENSE
python_google_weather_api-0.0.4.dist-info/METADATA
python_google_weather_api-0.0.4.dist-info/WHEEL
python_google_weather_api-0.0.4.dist-info/top_level.txt
python_google_weather_api-0.0.4.dist-info/RECORD
