Metadata-Version: 2.4
Name: python-google-weather-api
Version: 0.0.4
Summary: A python client library for Google Weather API
Author-email: tronikos <tronikos@gmail.com>
License-Expression: Apache-2.0
Project-URL: Homepage, https://github.com/tronikos/python-google-weather-api
Project-URL: Bug Tracker, https://github.com/tronikos/python-google-weather-api/issues
Requires-Python: >=3.11
License-File: LICENSE
Requires-Dist: aiohttp>=3.8
Requires-Dist: mashumaro
Provides-Extra: dev
Requires-Dist: pytest>=7; extra == "dev"
Dynamic: license-file
